{
  "date": "2026-04-17",
  "generated_at": "2026-04-17T00:42:30.916343",
  "data_source": "kiwoom",
  "macro_events": [
    {
      "title": "AI반도체",
      "summary": "TSMC 이익 58% 상승(AI 수요) → SK하이닉스·삼성 영업익 최대·차세대 협력 강화 → 한국 반도체 섹터 연속 강세"
    },
    {
      "title": "인프라투자",
      "summary": "정부가 가덕도신공항 2035년 개항 목표 + 원전 정책 강화 추진 → 대우건설 등 건설·에너지 섹터 성장 모멘텀 형성"
    },
    {
      "title": "K원전",
      "summary": "미-이란 전쟁·에너지 위기 → 한국 K-원전 수주 기대 → 대우건설 목표가 4배 상향, 정부 정책 강력 지원"
    },
    {
      "title": "중동갈등",
      "summary": "이란-이스라엘 갈등 고조로 중동 에너지 공급 불안 심화 & 유럽 항공유 부족 위기 → K-원전·신재생·방산주 위상 상승"
    },
    {
      "title": "머스크협력",
      "summary": "머스크가 삼성중공업·현대차 방문 → K-방산·우주항공·로봇 산업 글로벌 기술동맹 형성 및 협력 가속화"
    },
    {
      "title": "이란위험",
      "summary": "미 해군 이란 봉쇄·전쟁 우려 → 중동 공급망 불안·에너지 위기 → 글로벌 국방비 증가·인플레이션 우려"
    },
    {
      "title": "중국경기",
      "summary": "중국 GDP 5% 성장(경기 회복 신호) → 글로벌 경기 호재·수출 수요 증가 → 한국 반도체·자동차·화학 수주"
    },
    {
      "title": "공급망",
      "summary": "삼성전자-LGD 파넬 협력·머스크 협력 강화 → 반도체 공급망 국제화·이종 산업 협력 확대 → 한국 핵심 소재 수출 증가"
    }
  ],
  "narratives": [],
  "stocks": []
}